lociPARSE/QAmodel_lociPARSE.pt
lociPARSE/__init__.py
lociPARSE/core.py
lociPARSE/feature_generation.py
lociPARSE/model.py
lociPARSE/utils.py
lociPARSE-0.1.1.dist-info/METADATA
lociPARSE-0.1.1.dist-info/WHEEL
lociPARSE-0.1.1.dist-info/entry_points.txt
lociPARSE-0.1.1.dist-info/top_level.txt
lociPARSE-0.1.1.dist-info/RECORD
