Metadata-Version: 2.1
Name: lociPARSE
Version: 0.1.1
Summary: lociPARSE: a locality-aware invariant point attention model for scoring RNA 3D structures
Home-page: UNKNOWN
Author: ['Sumit Tarafder and Debswapna Bhattacharya']
License: UNKNOWN
Platform: UNKNOWN
Requires-Dist: numpy (==1.22.3)
Requires-Dist: tqdm (==4.64.0)
Requires-Dist: torch (==1.12.0)
